pysnptools/__init__.py
pysnptools/test.py
pysnptools/distreader/__init__.py
pysnptools/distreader/_distmergesids.py
pysnptools/distreader/_snp2dist.py
pysnptools/distreader/_subset.py
pysnptools/distreader/bgen.py
pysnptools/distreader/distdata.py
pysnptools/distreader/distgen.py
pysnptools/distreader/disthdf5.py
pysnptools/distreader/distmemmap.py
pysnptools/distreader/distnpz.py
pysnptools/distreader/distreader.py
pysnptools/distreader/test.py
pysnptools/distreader/test_bgen2.py
pysnptools/kernelreader/__init__.py
pysnptools/kernelreader/_subset.py
pysnptools/kernelreader/identity.py
pysnptools/kernelreader/kerneldata.py
pysnptools/kernelreader/kernelhdf5.py
pysnptools/kernelreader/kernelnpz.py
pysnptools/kernelreader/kernelreader.py
pysnptools/kernelreader/snpkernel.py
pysnptools/kernelreader/test.py
pysnptools/kernelstandardizer/__init__.py
pysnptools/pstreader/__init__.py
pysnptools/pstreader/_mergecols.py
pysnptools/pstreader/_mergerows.py
pysnptools/pstreader/_oneshot.py
pysnptools/pstreader/_subset.py
pysnptools/pstreader/pstdata.py
pysnptools/pstreader/psthdf5.py
pysnptools/pstreader/pstmemmap.py
pysnptools/pstreader/pstnpz.py
pysnptools/pstreader/pstreader.py
pysnptools/pstreader/test.py
pysnptools/snpreader/__init__.py
pysnptools/snpreader/_dist2snp.py
pysnptools/snpreader/_mergeiids.py
pysnptools/snpreader/_mergesids.py
pysnptools/snpreader/_subset.py
pysnptools/snpreader/bed.py
pysnptools/snpreader/dat.py
pysnptools/snpreader/dense.py
pysnptools/snpreader/distributedbed.py
pysnptools/snpreader/pairs.py
pysnptools/snpreader/ped.py
pysnptools/snpreader/pheno.py
pysnptools/snpreader/snpdata.py
pysnptools/snpreader/snpgen.py
pysnptools/snpreader/snphdf5.py
pysnptools/snpreader/snpmemmap.py
pysnptools/snpreader/snpnpz.py
pysnptools/snpreader/snpreader.py
pysnptools/snpreader/wrap_plink_parser.py
pysnptools/standardizer/__init__.py
pysnptools/standardizer/beta.py
pysnptools/standardizer/betatrained.py
pysnptools/standardizer/bysidcount.py
pysnptools-0.4.23.dist-info/AUTHORS.txt
pysnptools-0.4.23.dist-info/LICENSE.md
pysnptools-0.4.23.dist-info/METADATA
pysnptools-0.4.23.dist-info/WHEEL
pysnptools-0.4.23.dist-info/top_level.txt
pysnptools-0.4.23.dist-info/RECORD
