Metadata-Version: 2.1
Name: pysnptools
Version: 0.4.23
Summary: PySnpTools
Home-page: https://fastlmm.github.io/
Author: FaST-LMM Team
Author-email: fastlmm-dev@python.org
License: Apache 2.0
Project-URL: Bug Tracker, https://github.com/fastlmm/PySnpTools/issues
Project-URL: Documentation, http://fastlmm.github.io/PySnpTools
Project-URL: Source Code, https://github.com/fastlmm/PySnpTools
Keywords: gwas bioinformatics sets intervals ranges regions plink genomics file-format reader genotype bed-format writer python snps
Platform: UNKNOWN
Classifier: Programming Language :: Python :: 3.7
Classifier: Programming Language :: Python :: 3.8
Classifier: Programming Language :: Python :: 3
Classifier: Programming Language :: Python
Requires-Dist: scipy (>=1.1.0)
Requires-Dist: numpy (>=1.11.3)
Requires-Dist: pandas (>=1.1.1)
Requires-Dist: psutil (>=5.6.3)
Requires-Dist: h5py (>=2.10.0)
Requires-Dist: dill (>=0.2.9)
Requires-Dist: bgen-reader (>=4.0.6)
Requires-Dist: bed-reader (>=0.1.1)
